main.py
Moms_Canning_Timer-0.3.0.dist-info/LICENSE.md
Moms_Canning_Timer-0.3.0.dist-info/METADATA
Moms_Canning_Timer-0.3.0.dist-info/WHEEL
Moms_Canning_Timer-0.3.0.dist-info/top_level.txt
Moms_Canning_Timer-0.3.0.dist-info/RECORD
