Metadata-Version: 2.1
Name: Moms-Canning-Timer
Version: 0.3.0
Summary: Customizable 15-minute stove top timers, created for preserving fruits and veggies for the winter.
Home-page: https://github.com/Dog-Face-Development/Moms-Canning-Timer
Author: willtheorangeguy
License: # GNU GENERAL PUBLIC LICENSE
Project-URL: Homepage, https://github.com/Dog-Face-Development/Moms-Canning-Timer
Project-URL: Bug Tracker, https://github.com/Dog-Face-Development/Moms-Canning-Timer/issues
Classifier: Development Status :: 3 - Alpha
Classifier: License :: OSI Approved :: GNU General Public License v3 (GPLv3)
Classifier: Natural Language :: English
Classifier: Operating System :: OS Independent
Classifier: Topic :: Utilities
Requires-Python: >=3.9
License-File: LICENSE.md
